README.md
setup.py
pb_amarder/__init__.py
pb_amarder/bar.py
pb_amarder.egg-info/PKG-INFO
pb_amarder.egg-info/SOURCES.txt
pb_amarder.egg-info/dependency_links.txt
pb_amarder.egg-info/not-zip-safe
pb_amarder.egg-info/top_level.txt