Metadata-Version: 2.1
Name: pb-amarder
Version: 0.2.5
Summary: Custom progress status, primarily for iterators.
Home-page: https://gitlab.com/alexander_marder/pb-amarder
Author: Alex Marder
Requires-Python: >3.6
